{
  "workspaces": [
    {
      "path": "c:\\Users\\sxc\\Downloads\\saveweb2zip-com-olyve-tanshcreative-com",
      "files": [
        [
          "c:\\Users\\sxc\\Downloads\\saveweb2zip-com-olyve-tanshcreative-com\\js\\superfish.js",
          {
            "path": "c:\\Users\\sxc\\Downloads\\saveweb2zip-com-olyve-tanshcreative-com\\js\\superfish.js",
            "relativePath": "js/superfish.js",
            "symbols": [],
            "imports": [],
            "exports": [],
            "lastModified": "2026-01-10T10:22:15.131Z",
            "hash": "7d0196dac7d6fc06dee40e7aa1e303b3"
          }
        ],
        [
          "c:\\Users\\sxc\\Downloads\\saveweb2zip-com-olyve-tanshcreative-com\\js\\masonry.min.js",
          {
            "path": "c:\\Users\\sxc\\Downloads\\saveweb2zip-com-olyve-tanshcreative-com\\js\\masonry.min.js",
            "relativePath": "js/masonry.min.js",
            "symbols": [],
            "imports": [],
            "exports": [],
            "lastModified": "2026-01-10T10:22:15.045Z",
            "hash": "3b3fc826e58fc554108e4a651c9c7848"
          }
        ],
        [
          "c:\\Users\\sxc\\Downloads\\saveweb2zip-com-olyve-tanshcreative-com\\js\\jquery.slicknav.js",
          {
            "path": "c:\\Users\\sxc\\Downloads\\saveweb2zip-com-olyve-tanshcreative-com\\js\\jquery.slicknav.js",
            "relativePath": "js/jquery.slicknav.js",
            "symbols": [],
            "imports": [],
            "exports": [],
            "lastModified": "2026-01-10T10:22:14.939Z",
            "hash": "5bc5d160776347799f76e569730a4e46"
          }
        ],
        [
          "c:\\Users\\sxc\\Downloads\\saveweb2zip-com-olyve-tanshcreative-com\\js\\jquery.easing.js",
          {
            "path": "c:\\Users\\sxc\\Downloads\\saveweb2zip-com-olyve-tanshcreative-com\\js\\jquery.easing.js",
            "relativePath": "js/jquery.easing.js",
            "symbols": [],
            "imports": [],
            "exports": [],
            "lastModified": "2026-01-10T10:22:14.680Z",
            "hash": "cc237e8db4facc2501735ca08595f942"
          }
        ],
        [
          "c:\\Users\\sxc\\Downloads\\saveweb2zip-com-olyve-tanshcreative-com\\js\\swiper.min.js",
          {
            "path": "c:\\Users\\sxc\\Downloads\\saveweb2zip-com-olyve-tanshcreative-com\\js\\swiper.min.js",
            "relativePath": "js/swiper.min.js",
            "symbols": [],
            "imports": [],
            "exports": [],
            "lastModified": "2026-01-10T10:22:15.270Z",
            "hash": "83e9b29f0086bba50d653f1cb8dedc3c"
          }
        ],
        [
          "c:\\Users\\sxc\\Downloads\\saveweb2zip-com-olyve-tanshcreative-com\\js\\jquery.min.js",
          {
            "path": "c:\\Users\\sxc\\Downloads\\saveweb2zip-com-olyve-tanshcreative-com\\js\\jquery.min.js",
            "relativePath": "js/jquery.min.js",
            "symbols": [],
            "imports": [],
            "exports": [],
            "lastModified": "2026-01-10T10:22:14.828Z",
            "hash": "826eb77e86b02ab7724fe3d0141ff87c"
          }
        ],
        [
          "c:\\Users\\sxc\\Downloads\\saveweb2zip-com-olyve-tanshcreative-com\\js\\jquery-numerator.min.js",
          {
            "path": "c:\\Users\\sxc\\Downloads\\saveweb2zip-com-olyve-tanshcreative-com\\js\\jquery-numerator.min.js",
            "relativePath": "js/jquery-numerator.min.js",
            "symbols": [],
            "imports": [],
            "exports": [],
            "lastModified": "2026-01-10T10:22:14.608Z",
            "hash": "4d43b2fcb5ef3e6afdcd539f46148514"
          }
        ],
        [
          "c:\\Users\\sxc\\Downloads\\saveweb2zip-com-olyve-tanshcreative-com\\js\\isotope.js",
          {
            "path": "c:\\Users\\sxc\\Downloads\\saveweb2zip-com-olyve-tanshcreative-com\\js\\isotope.js",
            "relativePath": "js/isotope.js",
            "symbols": [],
            "imports": [],
            "exports": [],
            "lastModified": "2026-01-10T10:22:14.414Z",
            "hash": "5fb7c19c9c51cfb99f5ff942629f0f21"
          }
        ],
        [
          "c:\\Users\\sxc\\Downloads\\saveweb2zip-com-olyve-tanshcreative-com\\js\\jquery-migrate.min.js",
          {
            "path": "c:\\Users\\sxc\\Downloads\\saveweb2zip-com-olyve-tanshcreative-com\\js\\jquery-migrate.min.js",
            "relativePath": "js/jquery-migrate.min.js",
            "symbols": [],
            "imports": [],
            "exports": [],
            "lastModified": "2026-01-10T10:22:14.532Z",
            "hash": "9ffeb32e2d9efbf8f70caabded242267"
          }
        ],
        [
          "c:\\Users\\sxc\\Downloads\\saveweb2zip-com-olyve-tanshcreative-com\\js\\webpack.runtime.min.js",
          {
            "path": "c:\\Users\\sxc\\Downloads\\saveweb2zip-com-olyve-tanshcreative-com\\js\\webpack.runtime.min.js",
            "relativePath": "js/webpack.runtime.min.js",
            "symbols": [],
            "imports": [],
            "exports": [],
            "lastModified": "2026-01-10T10:22:15.342Z",
            "hash": "caf653d165739dc6e46c002035dbb551"
          }
        ],
        [
          "c:\\Users\\sxc\\Downloads\\saveweb2zip-com-olyve-tanshcreative-com\\js\\imagesloaded.min.js",
          {
            "path": "c:\\Users\\sxc\\Downloads\\saveweb2zip-com-olyve-tanshcreative-com\\js\\imagesloaded.min.js",
            "relativePath": "js/imagesloaded.min.js",
            "symbols": [],
            "imports": [],
            "exports": [],
            "lastModified": "2026-01-10T10:22:14.135Z",
            "hash": "6823120876c9afc8929418c9a6f8e343"
          }
        ],
        [
          "c:\\Users\\sxc\\Downloads\\saveweb2zip-com-olyve-tanshcreative-com\\js\\index_1.js",
          {
            "path": "c:\\Users\\sxc\\Downloads\\saveweb2zip-com-olyve-tanshcreative-com\\js\\index_1.js",
            "relativePath": "js/index_1.js",
            "symbols": [],
            "imports": [],
            "exports": [],
            "lastModified": "2026-01-10T10:22:14.308Z",
            "hash": "2912c657d0592cc532dff73d0d2ce7bb"
          }
        ],
        [
          "c:\\Users\\sxc\\Downloads\\saveweb2zip-com-olyve-tanshcreative-com\\js\\hoverIntent.min.js",
          {
            "path": "c:\\Users\\sxc\\Downloads\\saveweb2zip-com-olyve-tanshcreative-com\\js\\hoverIntent.min.js",
            "relativePath": "js/hoverIntent.min.js",
            "symbols": [],
            "imports": [],
            "exports": [],
            "lastModified": "2026-01-10T10:22:13.971Z",
            "hash": "8c0498e2f1f7a684a8d2a3feb934b64b"
          }
        ],
        [
          "c:\\Users\\sxc\\Downloads\\saveweb2zip-com-olyve-tanshcreative-com\\js\\i18n.min.js",
          {
            "path": "c:\\Users\\sxc\\Downloads\\saveweb2zip-com-olyve-tanshcreative-com\\js\\i18n.min.js",
            "relativePath": "js/i18n.min.js",
            "symbols": [],
            "imports": [],
            "exports": [],
            "lastModified": "2026-01-10T10:22:14.049Z",
            "hash": "3a5838d1182eb0b11f5a58bfe26e2529"
          }
        ],
        [
          "c:\\Users\\sxc\\Downloads\\saveweb2zip-com-olyve-tanshcreative-com\\js\\hooks.min.js",
          {
            "path": "c:\\Users\\sxc\\Downloads\\saveweb2zip-com-olyve-tanshcreative-com\\js\\hooks.min.js",
            "relativePath": "js/hooks.min.js",
            "symbols": [],
            "imports": [],
            "exports": [],
            "lastModified": "2026-01-10T10:22:13.890Z",
            "hash": "90e932bd9e62583fc494c00498cfe7f5"
          }
        ],
        [
          "c:\\Users\\sxc\\Downloads\\saveweb2zip-com-olyve-tanshcreative-com\\js\\index.js",
          {
            "path": "c:\\Users\\sxc\\Downloads\\saveweb2zip-com-olyve-tanshcreative-com\\js\\index.js",
            "relativePath": "js/index.js",
            "symbols": [],
            "imports": [],
            "exports": [],
            "lastModified": "2026-01-10T10:22:14.228Z",
            "hash": "96e7dc3f0e8559e4a3f3ca40b17ab9c3"
          }
        ],
        [
          "c:\\Users\\sxc\\Downloads\\saveweb2zip-com-olyve-tanshcreative-com\\js\\dtr-widgets.js",
          {
            "path": "c:\\Users\\sxc\\Downloads\\saveweb2zip-com-olyve-tanshcreative-com\\js\\dtr-widgets.js",
            "relativePath": "js/dtr-widgets.js",
            "symbols": [],
            "imports": [],
            "exports": [],
            "lastModified": "2026-01-10T10:22:13.594Z",
            "hash": "51047c0e97846d1da02ec3d7e807722f"
          }
        ],
        [
          "c:\\Users\\sxc\\Downloads\\saveweb2zip-com-olyve-tanshcreative-com\\js\\frontend.min.js",
          {
            "path": "c:\\Users\\sxc\\Downloads\\saveweb2zip-com-olyve-tanshcreative-com\\js\\frontend.min.js",
            "relativePath": "js/frontend.min.js",
            "symbols": [],
            "imports": [],
            "exports": [],
            "lastModified": "2026-01-10T10:22:13.802Z",
            "hash": "ceb183b138eac316a5cb0741ec23696a"
          }
        ],
        [
          "c:\\Users\\sxc\\Downloads\\saveweb2zip-com-olyve-tanshcreative-com\\js\\frontend-modules.min.js",
          {
            "path": "c:\\Users\\sxc\\Downloads\\saveweb2zip-com-olyve-tanshcreative-com\\js\\frontend-modules.min.js",
            "relativePath": "js/frontend-modules.min.js",
            "symbols": [],
            "imports": [],
            "exports": [],
            "lastModified": "2026-01-10T10:22:13.711Z",
            "hash": "4ca68d9d6badb02cd33799e1391e6305"
          }
        ],
        [
          "c:\\Users\\sxc\\Downloads\\saveweb2zip-com-olyve-tanshcreative-com\\js\\custom.js",
          {
            "path": "c:\\Users\\sxc\\Downloads\\saveweb2zip-com-olyve-tanshcreative-com\\js\\custom.js",
            "relativePath": "js/custom.js",
            "symbols": [],
            "imports": [],
            "exports": [],
            "lastModified": "2026-01-10T10:22:13.519Z",
            "hash": "4de1d0cae0a569d03d5cad52c33a41e3"
          }
        ],
        [
          "c:\\Users\\sxc\\Downloads\\saveweb2zip-com-olyve-tanshcreative-com\\js\\core.min.js",
          {
            "path": "c:\\Users\\sxc\\Downloads\\saveweb2zip-com-olyve-tanshcreative-com\\js\\core.min.js",
            "relativePath": "js/core.min.js",
            "symbols": [],
            "imports": [],
            "exports": [],
            "lastModified": "2026-01-10T10:22:13.432Z",
            "hash": "da215ae12b95b3aeeb2047667016c7f8"
          }
        ]
      ],
      "configFiles": []
    }
  ],
  "symbols": [],
  "lastIndexed": "2026-01-14T06:47:15.172Z",
  "version": "1.0"
}